pydra/tasks/ants/__init__.py
pydra/tasks/ants/_version.py
pydra/tasks/ants/latest.py
pydra/tasks/ants/auto/__init__.py
pydra/tasks/ants/auto/_post_release.py
pydra/tasks/ants/auto/base.py
pydra/tasks/ants/auto/legacy/__init__.py
pydra/tasks/ants/auto/legacy/ants_introduction.py
pydra/tasks/ants/auto/legacy/buildtemplateparallel.py
pydra/tasks/ants/auto/legacy/gen_warp_fields.py
pydra/tasks/ants/auto/legacy/tests/conftest.py
pydra/tasks/ants/auto/legacy/tests/test_antsintroduction.py
pydra/tasks/ants/auto/legacy/tests/test_buildtemplateparallel.py
pydra/tasks/ants/auto/legacy/tests/test_genwarpfields.py
pydra/tasks/ants/auto/nipype_ports/__init__.py
pydra/tasks/ants/auto/nipype_ports/interfaces/__init__.py
pydra/tasks/ants/auto/nipype_ports/interfaces/base/__init__.py
pydra/tasks/ants/auto/nipype_ports/interfaces/base/core.py
pydra/tasks/ants/auto/registration/__init__.py
pydra/tasks/ants/auto/registration/ants.py
pydra/tasks/ants/auto/registration/composite_transform_util.py
pydra/tasks/ants/auto/registration/measure_image_similarity.py
pydra/tasks/ants/auto/registration/registration.py
pydra/tasks/ants/auto/registration/registration_syn_quick.py
pydra/tasks/ants/auto/registration/tests/conftest.py
pydra/tasks/ants/auto/registration/tests/test_ants.py
pydra/tasks/ants/auto/registration/tests/test_compositetransformutil.py
pydra/tasks/ants/auto/registration/tests/test_measureimagesimilarity.py
pydra/tasks/ants/auto/registration/tests/test_registration.py
pydra/tasks/ants/auto/registration/tests/test_registrationsynquick.py
pydra/tasks/ants/auto/resampling/__init__.py
pydra/tasks/ants/auto/resampling/apply_transforms.py
pydra/tasks/ants/auto/resampling/apply_transforms_to_points.py
pydra/tasks/ants/auto/resampling/warp_image_multi_transform.py
pydra/tasks/ants/auto/resampling/warp_time_series_image_multi_transform.py
pydra/tasks/ants/auto/resampling/tests/conftest.py
pydra/tasks/ants/auto/resampling/tests/test_applytransforms.py
pydra_ants-0.1.0.dist-info/METADATA
pydra_ants-0.1.0.dist-info/WHEEL
pydra_ants-0.1.0.dist-info/licenses/LICENSE
pydra_ants-0.1.0.dist-info/licenses/NOTICE
pydra_ants-0.1.0.dist-info/RECORD
